menuplaceholder/__init__.py
menuplaceholder/__init__.pyc
menuplaceholder/admin.py
menuplaceholder/admin.pyc
menuplaceholder/models.py
menuplaceholder/models.pyc
menuplaceholder/templates/pages/menus/breadcrumb.html
menuplaceholder/templates/pages/menus/dropdown.html
menuplaceholder/templates/pages/menus/footer.html
menuplaceholder/templates/pages/menus/footer_tree.html
menuplaceholder/templates/pages/menus/mobile.html
menuplaceholder/templates/pages/menus/primary.html
menuplaceholder/templates/pages/menus/tree.html
menuplaceholder-0.1.6.dist-info/METADATA
menuplaceholder-0.1.6.dist-info/RECORD
menuplaceholder-0.1.6.dist-info/WHEEL
menuplaceholder-0.1.6.dist-info/top_level.txt
