Metadata-Version: 2.1
Name: menuplaceholder
Version: 0.1.6
Summary: Placeholder items for Mezzanine menus.
Home-page: UNKNOWN
Author: Peter Murphy
Author-email: peterkmurphy@gmail.com
License: LICENSE.txt
Platform: UNKNOWN
Classifier: Environment :: Web Environment
Classifier: Framework :: Django
Classifier: Intended Audience :: Developers
Classifier: License :: OSI Approved :: GNU General Public License v3 (GPLv3)
Classifier: Programming Language :: Python
Classifier: Operating System :: OS Independent
Requires-Dist: Django (>=1.0)
Requires-Dist: Mezzanine (>=4.0)
